[
{
"assetName" : "Dash" 
,
 "assetType" : "coin" 
,
 "assetTicker" : "DASH" 
,
 "block" : 1143581 
,
 "current_price" : 70.39 
,
 "market_cap" : 638241518 
,
 "total_volume" : 415974070 
,
 "blockchainAge" : "179325081"
,
 "price_change_percentage_24h" : -17.34951 
,
 "nTx" : "18"
 },
{
"assetName" : "Polis" 
,
 "assetType" : "coin" 
,
 "assetTicker" : "POLIS" 
,
 "block" : 442746 
,
 "current_price" : 0.574715 
,
 "market_cap" : 0 
,
 "total_volume" : 4653.39 
,
 "blockchainAge" : "55565392"
,
 "price_change_percentage_24h" : -15.56321 
,
 "nTx" : "3"
 },
{
"assetName" : "Adeptio" 
,
 "assetType" : "coin" 
,
 "assetTicker" : "ADE" 
,
 "block" : 656821 
,
 "current_price" : 0.00033577 
,
 "market_cap" : 0 
,
 "total_volume" : 0.167716 
,
 "blockchainAge" : "41718661"
,
 "price_change_percentage_24h" : -11.74287 
,
 "nTx" : "2"
 },
{
"assetName" : "Pivx" 
,
 "assetType" : "coin" 
,
 "assetTicker" : "PIVX" 
,
 "block" : 2003754 
,
 "current_price" : 0.183673 
,
 "market_cap" : 11214117 
,
 "total_volume" : 1163043 
,
 "blockchainAge" : "115301761"
,
 "price_change_percentage_24h" : -20.46028 
,
 "nTx" : "2"
 },
{
"assetName" : "Ontology" 
,
 "assetType" : "platform" 
,
 "assetTicker" : "ONT" 
,
 "block" : 1624373 
,
 "current_price" : 0.605955 
,
 "market_cap" : 394139090 
,
 "total_volume" : 165427529 
,
 "blockchainAge" : "39040279"
,
 "price_change_percentage_24h" : -15.90715 
,
 "nTx" : "2"
 },
{
"assetName" : "Bitcoin" 
,
 "assetType" : "coin" 
,
 "assetTicker" : "BTC" 
,
 "block" : 501542 
,
 "current_price" : 8324.58 
,
 "market_cap" : "149482019686" 
,
 "total_volume" : "31443681496" 
,
 "blockchainAge" : "337959106"
,
 "price_change_percentage_24h" : -12.6957 
,
 "nTx" : "2284"
 },
{
"assetName" : "Gincoin" 
,
 "assetType" : "coin" 
,
 "assetTicker" : "GIN" 
,
 "block" : 395266 
,
 "current_price" : 0.01447297 
,
 "market_cap" : 103495 
,
 "total_volume" : 11508.77 
,
 "blockchainAge" : "50042389"
,
 "price_change_percentage_24h" : -37.63267 
,
 "nTx" : "1"
 },
{
"assetName" : "Snowgem" 
,
 "assetType" : "coin" 
,
 "assetTicker" : "XSG" 
,
 "block" : 916380 
,
 "current_price" : 0.02752448 
,
 "market_cap" : 502250 
,
 "total_volume" : 94881 
,
 "blockchainAge" : "55394293"
,
 "price_change_percentage_24h" : -20.75115 
,
 "nTx" : "3"
 },
{
"assetName" : "Zcoin" 
,
 "assetType" : "coin" 
,
 "assetTicker" : "XZC" 
,
 "block" : 200558 
,
 "current_price" : 4.34 
,
 "market_cap" : 36633621 
,
 "total_volume" : 17749187 
,
 "blockchainAge" : "94407963"
,
 "price_change_percentage_24h" : -14.84947 
,
 "nTx" : "5"
 },
{
"assetName" : "Syscoin" 
,
 "assetType" : "coin" 
,
 "assetTicker" : "SYS" 
,
 "block" : 170027 
,
 "current_price" : 0.02057552 
,
 "market_cap" : 11597459 
,
 "total_volume" : 4495275 
,
 "blockchainAge" : "9751171"
,
 "price_change_percentage_24h" : -13.70052 
,
 "nTx" : "1"
}
]
