[
{
"assetName" : "Horizen" 
,
 "assetType" : "coin" 
,
 "assetTicker" : "ZEN" 
,
 "block" : 619233 
,
 "current_price" : 4.83 
,
 "market_cap" : 37390775 
,
 "total_volume" : 875773 
,
 "blockchainAge" : "95075865"
,
 "price_change_percentage_24h" : 0.18296 
,
 "nTx" : "12"
 },
{
"assetName" : "Dash" 
,
 "assetType" : "coin" 
,
 "assetTicker" : "DASH" 
,
 "block" : 1169343 
,
 "current_price" : 71.02 
,
 "market_cap" : 645516806 
,
 "total_volume" : 423917100 
,
 "blockchainAge" : "183386431"
,
 "price_change_percentage_24h" : -0.29682 
,
 "nTx" : "56"
 },
{
"assetName" : "Polis" 
,
 "assetType" : "coin" 
,
 "assetTicker" : "POLIS" 
,
 "block" : 474642 
,
 "current_price" : 1.09 
,
 "market_cap" : 0 
,
 "total_volume" : 139336 
,
 "blockchainAge" : "59626743"
,
 "price_change_percentage_24h" : -5.50038 
,
 "nTx" : "4"
 },
{
"assetName" : "Adeptio" 
,
 "assetType" : "coin" 
,
 "assetTicker" : "ADE" 
,
 "block" : 725763 
,
 "current_price" : 0.00008701 
,
 "market_cap" : 0 
,
 "total_volume" : 0.03598905 
,
 "blockchainAge" : "45780012"
,
 "price_change_percentage_24h" : -50.62326 
,
 "nTx" : "2"
 },
{
"assetName" : "Pivx" 
,
 "assetType" : "coin" 
,
 "assetTicker" : "PIVX" 
,
 "block" : 2071563 
,
 "current_price" : 0.237077 
,
 "market_cap" : 14585237 
,
 "total_volume" : 1035391 
,
 "blockchainAge" : "119363113"
,
 "price_change_percentage_24h" : 1.46217 
,
 "nTx" : "2"
 },
{
"assetName" : "Bitcoin" 
,
 "assetType" : "coin" 
,
 "assetTicker" : "BTC" 
,
 "block" : 603322 
,
 "current_price" : 8727.41 
,
 "market_cap" : "157457616630" 
,
 "total_volume" : "25938936840" 
,
 "blockchainAge" : "342020457"
,
 "price_change_percentage_24h" : -2.8212 
,
 "nTx" : "2944"
 },
{
"assetName" : "Snowgem" 
,
 "assetType" : "coin" 
,
 "assetTicker" : "XSG" 
,
 "block" : 983614 
,
 "current_price" : 0.01924164 
,
 "market_cap" : 376984 
,
 "total_volume" : 34320 
,
 "blockchainAge" : "59455644"
,
 "price_change_percentage_24h" : -4.76541 
,
 "nTx" : "3"
 },
{
"assetName" : "Zcoin" 
,
 "assetType" : "coin" 
,
 "assetTicker" : "XZC" 
,
 "block" : 214079 
,
 "current_price" : 4.7 
,
 "market_cap" : 41438734 
,
 "total_volume" : 9482201 
,
 "blockchainAge" : "98469315"
,
 "price_change_percentage_24h" : -4.47022 
,
 "nTx" : "4"
 },
{
"assetName" : "Syscoin" 
,
 "assetType" : "coin" 
,
 "assetTicker" : "SYS" 
,
 "block" : 236660 
,
 "current_price" : 0.02435565 
,
 "market_cap" : 13935090 
,
 "total_volume" : 985411 
,
 "blockchainAge" : "13812524"
,
 "price_change_percentage_24h" : -2.46488 
,
 "nTx" : "1"
 },
{
"assetName" : "Litecoin" 
,
 "assetType" : "coin" 
,
 "assetTicker" : "LTC" 
,
 "block" : 1734665 
,
 "current_price" : 62.11 
,
 "market_cap" : "3954498704" 
,
 "total_volume" : "3002338489" 
,
 "blockchainAge" : "255434773"
,
 "price_change_percentage_24h" : -3.91625 
,
 "nTx" : "17"
 },
{
"assetName" : "Ravencoin" 
,
 "assetType" : "coin" 
,
 "assetTicker" : "RVN" 
,
 "block" : 966332 
,
 "current_price" : 0.02808933 
,
 "market_cap" : 135893533 
,
 "total_volume" : 10252530 
,
 "blockchainAge" : "58474412"
,
 "price_change_percentage_24h" : -3.67213 
,
 "nTx" : "2"
 },
{
"assetName" : "Decred" 
,
 "assetType" : "coin" 
,
 "assetTicker" : "DCR" 
,
 "block" : 396288 
,
 "current_price" : 20.77 
,
 "market_cap" : 221357288 
,
 "total_volume" : 23148392 
,
 "blockchainAge" : "118535602"
,
 "price_change_percentage_24h" : 0.50584 
,
 "nTx" : "4"
 },
{
"assetName" : "Solaris" 
,
 "assetType" : "coin" 
,
 "assetTicker" : "XLR" 
,
 "block" : 13915 
,
 "current_price" : 0.256845 
,
 "market_cap" : 454860 
,
 "total_volume" : 98.08 
,
 "blockchainAge" : "1135103"
,
 "price_change_percentage_24h" : -0.00511 
,
 "nTx" : "2"
}
]
