[
{
"assetName" : "Dash" 
,
 "assetType" : "coin" 
,
 "assetTicker" : "DASH" 
,
 "block" : 1141339 
,
 "current_price" : 94.35 
,
 "market_cap" : 853171433 
,
 "total_volume" : 269364430 
,
 "blockchainAge" : "178971861"
,
 "price_change_percentage_24h" : -2.95511 
,
 "nTx" : "1"
 },
{
"assetName" : "Polis" 
,
 "assetType" : "coin" 
,
 "assetTicker" : "POLIS" 
,
 "block" : 439933 
,
 "current_price" : 0.624421 
,
 "market_cap" : 0 
,
 "total_volume" : 17295.66 
,
 "blockchainAge" : "55212171"
,
 "price_change_percentage_24h" : -0.30505 
,
 "nTx" : "2"
 },
{
"assetName" : "Adeptio" 
,
 "assetType" : "coin" 
,
 "assetTicker" : "ADE" 
,
 "block" : 88637 
,
 "current_price" : 0.00050802 
,
 "market_cap" : 0 
,
 "total_volume" : 0.01522541 
,
 "blockchainAge" : "41365439"
,
 "price_change_percentage_24h" : 68.67057 
,
 "nTx" : "1"
 },
{
"assetName" : "Pivx" 
,
 "assetType" : "coin" 
,
 "assetTicker" : "PIVX" 
,
 "block" : 1515222 
,
 "current_price" : 0.267492 
,
 "market_cap" : 16348138 
,
 "total_volume" : 5363524 
,
 "blockchainAge" : "114948538"
,
 "price_change_percentage_24h" : -2.63493 
,
 "nTx" : "2"
 },
{
"assetName" : "Ontology" 
,
 "assetType" : "platform" 
,
 "assetTicker" : "ONT" 
,
 "block" : 797327 
,
 "current_price" : 0.814473 
,
 "market_cap" : 530996793 
,
 "total_volume" : 113463718 
,
 "blockchainAge" : "38687056"
,
 "price_change_percentage_24h" : -0.26811 
,
 "nTx" : "1"
 },
{
"assetName" : "Bitcoin" 
,
 "assetType" : "coin" 
,
 "assetTicker" : "BTC" 
,
 "block" : 129086 
,
 "current_price" : 9985.56 
,
 "market_cap" : "179375864945" 
,
 "total_volume" : "17277303436" 
,
 "blockchainAge" : "337605882"
,
 "price_change_percentage_24h" : -1.95326 
,
 "nTx" : "11"
 },
{
"assetName" : "Gincoin" 
,
 "assetType" : "coin" 
,
 "assetTicker" : "GIN" 
,
 "block" : 392444 
,
 "current_price" : 0.01728594 
,
 "market_cap" : 122879 
,
 "total_volume" : 4017.84 
,
 "blockchainAge" : "49689164"
,
 "price_change_percentage_24h" : 2.07759 
,
 "nTx" : "1"
 },
{
"assetName" : "Snowgem" 
,
 "assetType" : "coin" 
,
 "assetTicker" : "XSG" 
,
 "block" : 910543 
,
 "current_price" : 0.03425552 
,
 "market_cap" : 621070 
,
 "total_volume" : 96700 
,
 "blockchainAge" : "55041068"
,
 "price_change_percentage_24h" : 10.73151 
,
 "nTx" : "1"
 },
{
"assetName" : "Zcoin" 
,
 "assetType" : "coin" 
,
 "assetTicker" : "XZC" 
,
 "block" : 199331 
,
 "current_price" : 5.7 
,
 "market_cap" : 48108752 
,
 "total_volume" : 22097883 
,
 "blockchainAge" : "94054737"
,
 "price_change_percentage_24h" : 6.81839 
,
 "nTx" : "3"
 },
{
"assetName" : "Syscoin" 
,
 "assetType" : "coin" 
,
 "assetTicker" : "SYS" 
,
 "block" : 164176 
,
 "current_price" : 0.02623858 
,
 "market_cap" : 14805240 
,
 "total_volume" : 5702628 
,
 "blockchainAge" : "9397945"
,
 "price_change_percentage_24h" : -2.03296 
,
 "nTx" : "1"
}
]
